nlproc/__init__.py
nlproc/hello.py
nlproc-0.0.1.dist-info/METADATA
nlproc-0.0.1.dist-info/WHEEL
nlproc-0.0.1.dist-info/licenses/LICENSE
nlproc-0.0.1.dist-info/RECORD
