Metadata-Version: 2.1
Name: NLProc
Version: 0.0.1
Summary: This repo is going to contain a very nice library featuring different NLP pipelines!
Project-URL: Homepage, https://github.com/caesar-one/nlproc
Project-URL: Bug Tracker, https://github.com/caesar-one/nlproc/issues
Author-email: Cesare Campagnano <cesare.campagnano@gmail.com>
License:                                  Apache License
Classifier: License :: OSI Approved :: MIT License
Classifier: Operating System :: OS Independent
Classifier: Programming Language :: Python :: 3
Requires-Python: >=3.7
